newrelic_sb_sdk/__init__.py
newrelic_sb_sdk/_modidx.py
newrelic_sb_sdk/client/__init__.py
newrelic_sb_sdk/graphql/__init__.py
newrelic_sb_sdk/graphql/enums.py
newrelic_sb_sdk/graphql/input_objects.py
newrelic_sb_sdk/graphql/objects.py
newrelic_sb_sdk/graphql/scalars.py
newrelic_sb_sdk/shortcuts/__init__.py
newrelic_sb_sdk/shortcuts/accounts.py
newrelic_sb_sdk/shortcuts/credentials.py
newrelic_sb_sdk/shortcuts/dashboards.py
newrelic_sb_sdk/shortcuts/historical_data_export.py
newrelic_sb_sdk/shortcuts/nrql.py
newrelic_sb_sdk/utils/__init__.py
newrelic_sb_sdk/utils/download.py
newrelic_sb_sdk/utils/exceptions.py
newrelic_sb_sdk/utils/query.py
newrelic_sb_sdk/utils/response.py
newrelic_sb_sdk/utils/text.py
newrelic_sb_sdk/version.py
newrelic_sb_sdk-0.44.0.dist-info/licenses/LICENSE.txt
newrelic_sb_sdk-0.44.0.dist-info/WHEEL
newrelic_sb_sdk-0.44.0.dist-info/METADATA
newrelic_sb_sdk-0.44.0.dist-info/RECORD
