Metadata-Version: 2.4
Name: newrelic-sb-sdk
Version: 0.44.0
Summary: New Relic SDK to interact with Nerdgraph API.
Keywords: Softbutterfly,New Relic,SDK,Nerdgraph,NRQL,API
Author: Dynova Development Team, zodiacfireworks
Author-email: Dynova Development Team <dev@dynova.io>, zodiacfireworks <martin.vuelta@gmail.com>
License-Expression: Apache-2.0
License-File: LICENSE.txt
Classifier: Development Status :: 4 - Beta
Classifier: Intended Audience :: Developers
Classifier: Intended Audience :: System Administrators
Classifier: Intended Audience :: Information Technology
Classifier: License :: OSI Approved :: Apache Software License
Classifier: Natural Language :: English
Classifier: Programming Language :: Python :: 3.10
Classifier: Programming Language :: Python :: 3.11
Classifier: Programming Language :: Python :: 3.12
Classifier: Programming Language :: Python :: 3.13
Classifier: Programming Language :: Python :: 3.14
Classifier: Topic :: Software Development
Classifier: Topic :: Software Development :: Libraries
Classifier: Topic :: Software Development :: Libraries :: Python Modules
Classifier: Topic :: System
Classifier: Topic :: System :: Monitoring
Classifier: Topic :: System :: Networking :: Monitoring
Requires-Dist: python-dotenv>=1.2.1,<2.0.0
Requires-Dist: requests>=2.32.5,<3.0.0
Requires-Dist: sgqlc>=17.1,<18.0.0
Maintainer: zodiacfireworks
Maintainer-email: zodiacfireworks <martin.vuelta@gmail.com>
Requires-Python: >=3.10.0, <4.0.0
Project-URL: Homepage, https://softbutterfly.gitlab.io/open-source/newrelic-sb-sdk
Project-URL: Repository, https://gitlab.com/softbutterfly/open-source/newrelic-sb-sdk
Project-URL: Documentation, https://softbutterfly.gitlab.io/open-source/newrelic-sb-sdk
Project-URL: Issues, https://gitlab.com/softbutterfly/open-source/newrelic-sb-sdk/-/issues
Project-URL: Download, https://gitlab.com/softbutterfly/open-source/newrelic-sb-sdk/-/archive/v0.44.0/newrelic-sb-sdk-v0.44.0.zip
Project-URL: Changelog, https://gitlab.com/softbutterfly/open-source/newrelic-sb-sdk/-/blob/v0.44.0/CHANGELOG.md
